testschong1/__init__.py
testschong1/test.py
testschong1/testpack.py
testschong1-1.0.5.dist-info/METADATA
testschong1-1.0.5.dist-info/WHEEL
testschong1-1.0.5.dist-info/top_level.txt
testschong1-1.0.5.dist-info/RECORD
